conjur/__init__.py
conjur/__main__.py
conjur/cli.py
conjur/cli_actions.py
conjur/config.py
conjur/constants.py
conjur/errors.py
conjur/errors_messages.py
conjur/resource.py
conjur/version.py
conjur/api/__init__.py
conjur/api/api.py
conjur/api/client.py
conjur/api/endpoints.py
conjur/api/errors.py
conjur/api/models/__init__.py
conjur/api/models/ssl_verification_metadata.py
conjur/api/models/ssl_verification_mode.py
conjur/api/ssl_utils/__init__.py
conjur/api/ssl_utils/errors.py
conjur/api/ssl_utils/ssl_client.py
conjur/api/ssl_utils/ssl_consts.py
conjur/api/ssl_utils/ssl_context_factory.py
conjur/argument_parser/__init__.py
conjur/argument_parser/_host_parser.py
conjur/argument_parser/_hostfactory_parser.py
conjur/argument_parser/_init_parser.py
conjur/argument_parser/_list_parser.py
conjur/argument_parser/_login_parser.py
conjur/argument_parser/_logout_parser.py
conjur/argument_parser/_policy_parser.py
conjur/argument_parser/_screen_options_parser.py
conjur/argument_parser/_user_parser.py
conjur/argument_parser/_variable_parser.py
conjur/argument_parser/_whoami_parser.py
conjur/argument_parser/argparse_builder.py
conjur/argument_parser/parser_utils.py
conjur/controller/__init__.py
conjur/controller/host_controller.py
conjur/controller/hostfactory_controller.py
conjur/controller/init_controller.py
conjur/controller/list_controller.py
conjur/controller/login_controller.py
conjur/controller/logout_controller.py
conjur/controller/policy_controller.py
conjur/controller/user_controller.py
conjur/controller/variable_controller.py
conjur/data_object/__init__.py
conjur/data_object/conjurrc_data.py
conjur/data_object/create_host_data.py
conjur/data_object/create_token_data.py
conjur/data_object/credentials_data.py
conjur/data_object/host_resource_data.py
conjur/data_object/list_data.py
conjur/data_object/list_members_of_data.py
conjur/data_object/list_permitted_roles_data.py
conjur/data_object/policy_data.py
conjur/data_object/user_input_data.py
conjur-7.1.0.dist-info/LICENSE.md
conjur-7.1.0.dist-info/METADATA
conjur-7.1.0.dist-info/NOTICES.txt
conjur-7.1.0.dist-info/WHEEL
conjur-7.1.0.dist-info/entry_points.txt
conjur-7.1.0.dist-info/top_level.txt
conjur-7.1.0.dist-info/zip-safe
conjur-7.1.0.dist-info/RECORD
