Metadata-Version: 2.1
Name: conjur
Version: 7.1.0
Summary: APIs for interacting with the Conjur v5 appliance
Home-page: https://github.com/conjurinc/conjur-api-python3
Author: CyberArk Software, Inc
Author-email: CyberArk Maintainers <conj_maintainers@cyberark.com>
License: MIT
Keywords: conjur,cyberark,microservicesprivileged access,security,vault
Platform: UNKNOWN
Classifier: Programming Language :: Python :: 3 :: Only
Classifier: Development Status :: 3 - Alpha
Classifier: Intended Audience :: Developers
Classifier: License :: OSI Approved :: MIT License
Classifier: Operating System :: OS Independent
Classifier: Natural Language :: English
Classifier: Topic :: Office/Business
Classifier: Topic :: Security
Classifier: Topic :: Security :: Cryptography
Classifier: Topic :: Software Development
Classifier: Topic :: Software Development :: Libraries
Classifier: Topic :: Software Development :: Libraries :: Python Modules
Classifier: Topic :: System :: Systems Administration
Classifier: Topic :: System :: Systems Administration :: Authentication/Directory
Classifier: Topic :: Utilities
Requires-Python: >=3.10.1
License-File: LICENSE.md
License-File: NOTICES.txt
Requires-Dist: nose2 (>=0.9.2)
Requires-Dist: nose2[coverage_plugin] (>=0.6.5)
Requires-Dist: pylint (>=2.6.0)
Requires-Dist: cryptography (~=3.3.2)
Requires-Dist: keyring (>=23.0.0)
Requires-Dist: pyopenssl (>=20.0.0)
Requires-Dist: PyInstaller (>=4.0)
Requires-Dist: PyYAML (>=5.3.1)
Requires-Dist: aiohttp (>=3.8.1)
Requires-Dist: asynctest (>=0.13.0)
Requires-Dist: setuptools (>=57.0.0)
Requires-Dist: twine (>=3.2.0)
Requires-Dist: urllib3 (>=1.25.9)
